data/__init__.py
data/config/__init__.py
premium/__init__.py
premium/config.py
premium/segment.py
premium/algorithm/__init__.py
premium/base/__init__.py
premium/base/pipeline.py
premium/corpus/__init__.py
premium/corpus/stopwords.py
premium/corpus/texts.py
premium/corpus/utils.py
premium/data/__init__.py
premium/data/_dict.py
premium/data/augumentation.py
premium/data/csv.py
premium/data/datasets.py
premium/data/eda.py
premium/data/loader.py
premium/data/ner.py
premium/data/postprocess.py
premium/data/preprocess.py
premium/data/utils.py
premium/data/classification/__init__.py
premium/experimental/__init__.py
premium/experimental/annotate.py
premium/experimental/cbow.py
premium/experimental/eda.py
premium/experimental/kaggle.py
premium/experimental/myfasttext.py
premium/experimental/nn_metric.py
premium/experimental/segment_train.py
premium/experimental/textnn.py
premium/lightning/__init__.py
premium/lightning/base.py
premium/lightning/callbacks.py
premium/metrics/__init__.py
premium/metrics/asr.py
premium/metrics/distance.py
premium/metrics/metrix.py
premium/models/__init__.py
premium/models/base.py
premium/models/benchmark.py
premium/models/bert.py
premium/models/binary_classifiers.py
premium/models/clf.py
premium/models/lgb.py
premium/models/model_config.py
premium/models/multi_classifier.py
premium/models/nn.py
premium/models/optuna.py
premium/models/regressor.py
premium/models/touchstone.py
premium/models/xgb.py
premium/models/classifiers/__init__.py
premium/models/classifiers/baseline.py
premium/models/classifiers/bases.py
premium/models/classifiers/dataset.py
premium/models/classifiers/tokenizers.py
premium/models/classifiers/tree_models.py
premium/models/classifiers/voting.py
premium/models/classifiers/binary/__init__.py
premium/models/classifiers/binary/benchmark.py
premium/models/classifiers/binary/bert.py
premium/models/classifiers/binary/lstm.py
premium/models/classifiers/binary/mlp.py
premium/models/classifiers/binary/nb.py
premium-23.12.18.18.dist-info/METADATA
premium-23.12.18.18.dist-info/WHEEL
premium-23.12.18.18.dist-info/entry_points.txt
premium-23.12.18.18.dist-info/top_level.txt
premium-23.12.18.18.dist-info/RECORD
